Workbook

Sheet Analysis_Base
A1: symbol | B1: year | C1: revenue | D1: gross_profit | E1: ebitda | F1: ebit | G1: operating_income | H1: net_income | I1: total_assets | J1: equity | K1: current_assets | L1: current_liabilities | M1: total_debt | N1: operating_cash_flow | O1: investing_cash_flow | P1: financing_cash_flow | Q1: free_cash_flow | R1: capital_expenditure
A2: ICBP | B2: 2020 | C2: 46641048000000 | D2: 17224375000000 | E2: 11083851000000 | F2: 10629192000000 | G2: 9417855000000 | H2: 6586907000000 | I2: 103588325000000.0 | J2: 29430291000000 | K2: 20716223000000 | L2: 9176164000000 | M2: 31724366000000 | N2: 9336780000000 | O2: -34957389000000 | P2: 26758085000000 | Q2: 7417610000000 | R2: -1919170000000
A3: ICBP | B3: 2021 | C3: 56803733000000 | D3: 20287284000000 | E3: 12249792000000 | F3: 11787247000000 | G3: 11914978000000 | H3: 6399431000000 | I3: 118015311000000.0 | J3: 34090000000000 | K3: 33997637000000 | L3: 18896133000000 | M3: 41752460000000 | N3: 7989039000000 | O3: -3100274000000 | P3: 5905745000000 | Q3: 5739288000000 | R3: -2249751000000
A4: ICBP | B4: 2022 | C4: 64797516000000 | D4: 21792286000000 | E4: 10137353000000 | F4: 9674042000000 | G4: 12832021000000 | H4: 4587367000000 | I4: 115305536000000.0 | J4: 36518511000000 | K4: 31070365000000 | L4: 10033935000000 | M4: 46006051000000 | N4: 8804494000000 | O4: -1505635000000 | P4: -12826259000000 | Q4: 7015618000000 | R4: -1788876000000
A5: ICBP | B5: 2023 | C5: 67909901000000 | D5: 25126260000000 | E5: 13843360000000 | F5: 13469406000000 | G5: 15038291000000 | H5: 6990572000000 | I5: 119267076000000.0 | J5: 40750169000000 | K5: 36773465000000 | L5: 10464225000000 | M5: 43990332000000 | N5: 12415005000000 | O5: -3987804000000 | P5: -4619785000000 | Q5: 10591175000000 | R5: -1823830000000
A6: INDF | B6: 2020 | C6: 81731469000000 | D6: 26755152000000 | E6: 15050427000000 | F6: 14302146000000 | G6: 12956352000000 | H6: 6455632000000 | I6: 163136516000000.0 | J6: 42374298000000 | K6: 38418238000000 | L6: 27975875000000 | M6: 53520426000000 | N6: 13855497000000 | O6: -37636597000000 | P6: 27285509000000 | Q6: 9263193000000 | R6: -4592304000000
A7: INDF | B7: 2021 | C7: 99345618000000 | D7: 32586794000000 | E7: 18131254000000 | F7: 17331536000000 | G7: 17515610000000 | H7: 7662254000000 | I7: 179271840000000.0 | J7: 48535675000000 | K7: 54183399000000 | L7: 40403404000000 | M7: 62030568000000 | N7: 14692641000000 | O7: -6489675000000 | P7: 3852424000000 | Q7: 9907973000000 | R7: -4784668000000
A8: INDF | B8: 2022 | C8: 110830272000000.0 | D8: 33971679000000 | E8: 16350531000000 | F8: 15524858000000 | G8: 18792599000000 | H8: 6359094000000 | I8: 180433300000000.0 | J8: 53843836000000 | K8: 54876668000000 | L8: 30725942000000 | M8: 66249057000000 | N8: 13624195000000 | O8: -3899503000000 | P8: -14329188000000 | Q8: 9645182000000 | R8: -3979013000000
A9: INDF | B9: 2023 | C9: 111703611000000.0 | D9: 36050469000000 | E9: 19861872000000 | F9: 19140009000000 | G9: 20144409000000 | H9: 8147019000000 | I9: 186587957000000.0 | J9: 59193013000000 | K9: 63101797000000 | L9: 32914504000000 | M9: 64692665000000 | N9: 18460624000000 | O9: -10775851000000 | P9: -4889846000000 | Q9: 14492760000000 | R9: -3967864000000
A10: MYOR | B10: 2020 | C10: 24476953742651 | D10: 7299122959685 | E10: 3165621987673 | F10: 3037712615943 | G10: 2857436314408 | H10: 2060631850945 | I10: 19777500514550 | J10: 11011069905567 | K10: 12838729162094 | L10: 3559336027729 | M10: 4860827484888 | N10: 3715832449186 | O10: -1111015237138 | P10: -1865848198703 | Q10: 2560230037616 | R10: -1155602411570
A11: MYOR | B11: 2021 | C11: 27904558322183 | D11: 6922983508403 | E11: 2001485741380 | F11: 1870183771326 | G11: 1804861101096 | H11: 1186598590767 | I11: 19917653265528 | J11: 11118707150388 | K11: 12969783874643 | L11: 5570773468770 | M11: 5133934187496 | N11: 1041955003348 | O11: -947614701926 | P11: -870693620125 | Q11: 64519013058 | R11: -977435990290
A12: MYOR | B12: 2022 | C12: 30669405967404 | D12: 6839423338924 | E12: 3019424332266 | F12: 2895240195831 | G12: 2466196699030 | H12: 1942229752036 | I12: 22276160695411 | J12: 12628400600637 | K12: 14772623976128 | L12: 5636627301308 | M12: 5529177853189 | N12: 1619570638186 | O12: -1546563424787 | P12: -49224058856 | Q12: 110355860242 | R12: -1509214777944
A13: MYOR | B13: 2023 | C13: 31485008185525 | D13: 8407777758683 | E13: 4517736259342 | F13: 4396292972270 | G13: 4335787550846 | H13: 3193816276615 | I13: 23870404962472 | J13: 15039487611663 | K13: 14738922387529 | L13: 4013200501414 | M13: 4267410076475 | N13: 5259181989696 | O13: -2359457241900 | P13: -1975978291736 | Q13: 2733452910514 | R13: -2525729079182
A14: UNVR | B14: 2020 | C14: 42972474000000 | D14: 22456990000000 | E14: 9927839000000 | F14: 9455659000000 | G14: 9451012000000 | H14: 7163536000000 | I14: 20534632000000 | J14: 4937368000000 | K14: 8828360000000 | L14: 13357536000000 | M14: 3974990000000 | N14: 8363993000000 | O14: -690216000000 | P14: -7458509000000 | Q14: 7672043000000 | R14: -691950000000
A15: UNVR | B15: 2021 | C15: 39545959000000 | D15: 19626387000000 | E15: 8120647000000 | F15: 7681468000000 | G15: 7679451000000 | H15: 5758148000000 | I15: 19068532000000 | J15: 4321269000000 | K15: 7642208000000 | L15: 12445152000000 | M15: 2736866000000 | N15: 7902091000000 | O15: -681255000000 | P15: -7739754000000 | Q15: 7215364000000 | R15: -686727000000
A16: UNVR | B16: 2022 | C16: 41218881000000 | D16: 19064937000000 | E16: 7504564000000 | F16: 7079014000000 | G16: 7068808000000 | H16: 5364761000000 | I16: 18318114000000 | J16: 3997256000000 | K16: 7567768000000 | L16: 12442223000000 | M16: 1284026000000 | N16: 8061314000000 | O16: -526063000000 | P16: -7357788000000 | Q16: 7422951000000 | R16: -638363000000
A17: UNVR | B17: 2023 | C17: 38611401000000 | D17: 19194514000000 | E17: 6690717000000 | F17: 6307846000000 | G17: 6279283000000 | H17: 4800940000000 | I17: 16664086000000 | J17: 3381238000000 | K17: 6191839000000 | L17: 11223968000000 | M17: 750783000000 | N17: 7118088000000 | O17: -829323000000 | P17: -5771276000000 | Q17: 6283060000000 | R17: -835028000000

Sheet Financial_Analysis
A1: Company | B1: year | C1: revenue | D1: ebitda | E1: ebit | F1: operating_income | G1: net_income | H1: total_assets | I1: equity | J1: total_debt | K1: gross_profit | L1: current_assets | M1: current_liabilities | N1: revenue_growth | O1: ebitda_growth | P1: net_income_growth | Q1: operating_cf_growth | R1: free_cash_flow_growth | S1: gross_margin | T1: ebitda_margin | U1: ebit_margin | V1: operating_margin | W1: net_margin | X1: roe | Y1: roa | Z1: current_ratio | AA1: debt_to_equity | AB1: debt_to_assets | AC1: equity_ratio | AD1: investing_cash_flow | AE1: financing_cash_flow | AF1: capital_expenditure | AG1: operating_cash_flow | AH1: free_cash_flow | AI1: ocf_margin | AJ1: fcf_margin | AK1: capex_to_ocf | AL1: equity_to_assets
A2: =Analysis_Base!A2 -> ICBP | B2: =Analysis_Base!B2 -> 2020 | C2: =VALUE(Analysis_Base!C2) -> 46641048000000 | D2: =VALUE(Analysis_Base!E2) -> 11083851000000 | E2: =VALUE(Analysis_Base!F2) -> 10629192000000 | F2: =VALUE(Analysis_Base!G2) -> 9417855000000 | G2: =VALUE(Analysis_Base!H2) -> 6586907000000 | H2: =VALUE(Analysis_Base!I2) -> 103588325000000 | I2: =VALUE(Analysis_Base!J2) -> 29430291000000 | J2: =VALUE(Analysis_Base!M2) -> 31724366000000 | K2: =VALUE(Analysis_Base!D2) -> 17224375000000 | L2: =VALUE(Analysis_Base!K2) -> 20716223000000 | M2: =VALUE(Analysis_Base!L2) -> 9176164000000 | N2: =IF(A2=A1,C2/C1-1,"") | O2: =IF(A2=A1,D2/D1-1,"") | P2: =IF(A2=A1,G2/G1-1,"") | Q2: =IF(A2=A1,AG2/AG1-1,"") | R2: =IF(A2=A1,AH2/AH1-1,"") | S2: =K2/C2 -> 0.36929648 | T2: =D2/C2 -> 0.23764155 | U2: =E2/C2 -> 0.22789351 | V2: =F2/C2 -> 0.20192203 | W2: =G2/C2 -> 0.14122554 | X2: =G2/I2 -> 0.22381386 | Y2: =G2/H2 -> 0.063587349 | Z2: =L2/M2 -> 2.2576125 | AA2: =J2/I2 -> 1.0779495 | AB2: =J2/H2 -> 0.30625426 | AC2: =I2/H2 -> 0.28410818 | AD2: =VALUE(Analysis_Base!O2) -> -34957389000000 | AE2: =VALUE(Analysis_Base!P2) -> 26758085000000 | AF2: =VALUE(Analysis_Base!R2) -> -1919170000000 | AG2: =VALUE(Analysis_Base!N2) -> 9336780000000 | AH2: =VALUE(Analysis_Base!Q2) -> 7417610000000 | AI2: =AG2/C2 -> 0.20018375 | AJ2: =AH2/C2 -> 0.15903609 | AK2: =ABS(AF2)/AG2 -> 0.20554945 | AL2: =I2/H2 -> 0.28410818
A3: =Analysis_Base!A3 -> ICBP | B3: =Analysis_Base!B3 -> 2021 | C3: =VALUE(Analysis_Base!C3) -> 56803733000000 | D3: =VALUE(Analysis_Base!E3) -> 12249792000000 | E3: =VALUE(Analysis_Base!F3) -> 11787247000000 | F3: =VALUE(Analysis_Base!G3) -> 11914978000000 | G3: =VALUE(Analysis_Base!H3) -> 6399431000000 | H3: =VALUE(Analysis_Base!I3) -> 118015311000000 | I3: =VALUE(Analysis_Base!J3) -> 34090000000000 | J3: =VALUE(Analysis_Base!M3) -> 41752460000000 | K3: =VALUE(Analysis_Base!D3) -> 20287284000000 | L3: =VALUE(Analysis_Base!K3) -> 33997637000000 | M3: =VALUE(Analysis_Base!L3) -> 18896133000000 | N3: =IF(A3=A2,C3/C2-1,"") -> 0.21789144 | O3: =IF(A3=A2,D3/D2-1,"") -> 0.10519277 | P3: =IF(A3=A2,G3/G2-1,"") -> -0.028461917 | Q3: =IF(A3=A2,AG3/AG2-1,"") -> -0.14434752 | R3: =IF(A3=A2,AH3/AH2-1,"") -> -0.22626183 | S3: =K3/C3 -> 0.35714702 | T3: =D3/C3 -> 0.21565118 | U3: =E3/C3 -> 0.20750832 | V3: =F3/C3 -> 0.20975695 | W3: =G3/C3 -> 0.11265863 | X3: =G3/I3 -> 0.18772165 | Y3: =G3/H3 -> 0.05422543 | Z3: =L3/M3 -> 1.7991849 | AA3: =J3/I3 -> 1.2247715 | AB3: =J3/H3 -> 0.3537885 | AC3: =I3/H3 -> 0.28886082 | AD3: =VALUE(Analysis_Base!O3) -> -3100274000000 | AE3: =VALUE(Analysis_Base!P3) -> 5905745000000 | AF3: =VALUE(Analysis_Base!R3) -> -2249751000000 | AG3: =VALUE(Analysis_Base!N3) -> 7989039000000 | AH3: =VALUE(Analysis_Base!Q3) -> 5739288000000 | AI3: =AG3/C3 -> 0.14064285 | AJ3: =AH3/C3 -> 0.10103716 | AK3: =ABS(AF3)/AG3 -> 0.28160471 | AL3: =I3/H3 -> 0.28886082
A4: =Analysis_Base!A4 -> ICBP | B4: =Analysis_Base!B4 -> 2022 | C4: =VALUE(Analysis_Base!C4) -> 64797516000000 | D4: =VALUE(Analysis_Base!E4) -> 10137353000000 | E4: =VALUE(Analysis_Base!F4) -> 9674042000000 | F4: =VALUE(Analysis_Base!G4) -> 12832021000000 | G4: =VALUE(Analysis_Base!H4) -> 4587367000000 | H4: =VALUE(Analysis_Base!I4) -> 115305536000000 | I4: =VALUE(Analysis_Base!J4) -> 36518511000000 | J4: =VALUE(Analysis_Base!M4) -> 46006051000000 | K4: =VALUE(Analysis_Base!D4) -> 21792286000000 | L4: =VALUE(Analysis_Base!K4) -> 31070365000000 | M4: =VALUE(Analysis_Base!L4) -> 10033935000000 | N4: =IF(A4=A3,C4/C3-1,"") -> 0.14072637 | O4: =IF(A4=A3,D4/D3-1,"") -> -0.17244693 | P4: =IF(A4=A3,G4/G3-1,"") -> -0.28316017 | Q4: =IF(A4=A3,AG4/AG3-1,"") -> 0.10207173 | R4: =IF(A4=A3,AH4/AH3-1,"") -> 0.22238473 | S4: =K4/C4 -> 0.3363136 | T4: =D4/C4 -> 0.15644663 | U4: =E4/C4 -> 0.14929649 | V4: =F4/C4 -> 0.19803261 | W4: =G4/C4 -> 0.070795414 | X4: =G4/I4 -> 0.12561758 | Y4: =G4/H4 -> 0.039784447 | Z4: =L4/M4 -> 3.0965284 | AA4: =J4/I4 -> 1.2598008 | AB4: =J4/H4 -> 0.39899256 | AC4: =I4/H4 -> 0.31671082 | AD4: =VALUE(Analysis_Base!O4) -> -1505635000000 | AE4: =VALUE(Analysis_Base!P4) -> -12826259000000 | AF4: =VALUE(Analysis_Base!R4) -> -1788876000000 | AG4: =VALUE(Analysis_Base!N4) -> 8804494000000 | AH4: =VALUE(Analysis_Base!Q4) -> 7015618000000 | AI4: =AG4/C4 -> 0.13587703 | AJ4: =AH4/C4 -> 0.10826986 | AK4: =ABS(AF4)/AG4 -> 0.2031776 | AL4: =I4/H4 -> 0.31671082
A5: =Analysis_Base!A5 -> ICBP | B5: =Analysis_Base!B5 -> 2023 | C5: =VALUE(Analysis_Base!C5) -> 67909901000000 | D5: =VALUE(Analysis_Base!E5) -> 13843360000000 | E5: =VALUE(Analysis_Base!F5) -> 13469406000000 | F5: =VALUE(Analysis_Base!G5) -> 15038291000000 | G5: =VALUE(Analysis_Base!H5) -> 6990572000000 | H5: =VALUE(Analysis_Base!I5) -> 119267076000000 | I5: =VALUE(Analysis_Base!J5) -> 40750169000000 | J5: =VALUE(Analysis_Base!M5) -> 43990332000000 | K5: =VALUE(Analysis_Base!D5) -> 25126260000000 | L5: =VALUE(Analysis_Base!K5) -> 36773465000000 | M5: =VALUE(Analysis_Base!L5) -> 10464225000000 | N5: =IF(A5=A4,C5/C4-1,"") -> 0.048032474 | O5: =IF(A5=A4,D5/D4-1,"") -> 0.36557936 | P5: =IF(A5=A4,G5/G4-1,"") -> 0.52387459 | Q5: =IF(A5=A4,AG5/AG4-1,"") -> 0.41007592 | R5: =IF(A5=A4,AH5/AH4-1,"") -> 0.50965674 | S5: =K5/C5 -> 0.36999406 | T5: =D5/C5 -> 0.20384892 | U5: =E5/C5 -> 0.1983423 | V5: =F5/C5 -> 0.22144475 | W5: =G5/C5 -> 0.10293892 | X5: =G5/I5 -> 0.17154707 | Y5: =G5/H5 -> 0.058612756 | Z5: =L5/M5 -> 3.5142082 | AA5: =J5/I5 -> 1.0795129 | AB5: =J5/H5 -> 0.36883886 | AC5: =I5/H5 -> 0.34167157 | AD5: =VALUE(Analysis_Base!O5) -> -3987804000000 | AE5: =VALUE(Analysis_Base!P5) -> -4619785000000 | AF5: =VALUE(Analysis_Base!R5) -> -1823830000000 | AG5: =VALUE(Analysis_Base!N5) -> 12415005000000 | AH5: =VALUE(Analysis_Base!Q5) -> 10591175000000 | AI5: =AG5/C5 -> 0.18281583 | AJ5: =AH5/C5 -> 0.15595922 | AK5: =ABS(AF5)/AG5 -> 0.1469053 | AL5: =I5/H5 -> 0.34167157
A6: =Analysis_Base!A6 -> INDF | B6: =Analysis_Base!B6 -> 2020 | C6: =VALUE(Analysis_Base!C6) -> 81731469000000 | D6: =VALUE(Analysis_Base!E6) -> 15050427000000 | E6: =VALUE(Analysis_Base!F6) -> 14302146000000 | F6: =VALUE(Analysis_Base!G6) -> 12956352000000 | G6: =VALUE(Analysis_Base!H6) -> 6455632000000 | H6: =VALUE(Analysis_Base!I6) -> 163136516000000 | I6: =VALUE(Analysis_Base!J6) -> 42374298000000 | J6: =VALUE(Analysis_Base!M6) -> 53520426000000 | K6: =VALUE(Analysis_Base!D6) -> 26755152000000 | L6: =VALUE(Analysis_Base!K6) -> 38418238000000 | M6: =VALUE(Analysis_Base!L6) -> 27975875000000 | N6: =IF(A6=A5,C6/C5-1,"") | O6: =IF(A6=A5,D6/D5-1,"") | P6: =IF(A6=A5,G6/G5-1,"") | Q6: =IF(A6=A5,AG6/AG5-1,"") | R6: =IF(A6=A5,AH6/AH5-1,"") | S6: =K6/C6 -> 0.32735435 | T6: =D6/C6 -> 0.18414482 | U6: =E6/C6 -> 0.17498946 | V6: =F6/C6 -> 0.15852342 | W6: =G6/C6 -> 0.07898588 | X6: =G6/I6 -> 0.15234782 | Y6: =G6/H6 -> 0.039571962 | Z6: =L6/M6 -> 1.3732631 | AA6: =J6/I6 -> 1.2630398 | AB6: =J6/H6 -> 0.3280714 | AC6: =I6/H6 -> 0.25974747 | AD6: =VALUE(Analysis_Base!O6) -> -37636597000000 | AE6: =VALUE(Analysis_Base!P6) -> 27285509000000 | AF6: =VALUE(Analysis_Base!R6) -> -4592304000000 | AG6: =VALUE(Analysis_Base!N6) -> 13855497000000 | AH6: =VALUE(Analysis_Base!Q6) -> 9263193000000 | AI6: =AG6/C6 -> 0.16952463 | AJ6: =AH6/C6 -> 0.11333692 | AK6: =ABS(AF6)/AG6 -> 0.33144275 | AL6: =I6/H6 -> 0.25974747
A7: =Analysis_Base!A7 -> INDF | B7: =Analysis_Base!B7 -> 2021 | C7: =VALUE(Analysis_Base!C7) -> 99345618000000 | D7: =VALUE(Analysis_Base!E7) -> 18131254000000 | E7: =VALUE(Analysis_Base!F7) -> 17331536000000 | F7: =VALUE(Analysis_Base!G7) -> 17515610000000 | G7: =VALUE(Analysis_Base!H7) -> 7662254000000 | H7: =VALUE(Analysis_Base!I7) -> 179271840000000 | I7: =VALUE(Analysis_Base!J7) -> 48535675000000 | J7: =VALUE(Analysis_Base!M7) -> 62030568000000 | K7: =VALUE(Analysis_Base!D7) -> 32586794000000 | L7: =VALUE(Analysis_Base!K7) -> 54183399000000 | M7: =VALUE(Analysis_Base!L7) -> 40403404000000 | N7: =IF(A7=A6,C7/C6-1,"") -> 0.21551245 | O7: =IF(A7=A6,D7/D6-1,"") -> 0.20470031 | P7: =IF(A7=A6,G7/G6-1,"") -> 0.18690997 | Q7: =IF(A7=A6,AG7/AG6-1,"") -> 0.06041963 | R7: =IF(A7=A6,AH7/AH6-1,"") -> 0.069606668 | S7: =K7/C7 -> 0.32801441 | T7: =D7/C7 -> 0.18250683 | U7: =E7/C7 -> 0.17445698 | V7: =F7/C7 -> 0.17630984 | W7: =G7/C7 -> 0.077127247 | X7: =G7/I7 -> 0.1578685 | Y7: =G7/H7 -> 0.042740979 | Z7: =L7/M7 -> 1.3410602 | AA7: =J7/I7 -> 1.2780407 | AB7: =J7/H7 -> 0.34601401 | AC7: =I7/H7 -> 0.27073786 | AD7: =VALUE(Analysis_Base!O7) -> -6489675000000 | AE7: =VALUE(Analysis_Base!P7) -> 3852424000000 | AF7: =VALUE(Analysis_Base!R7) -> -4784668000000 | AG7: =VALUE(Analysis_Base!N7) -> 14692641000000 | AH7: =VALUE(Analysis_Base!Q7) -> 9907973000000 | AI7: =AG7/C7 -> 0.1478942 | AJ7: =AH7/C7 -> 0.099732361 | AK7: =ABS(AF7)/AG7 -> 0.32565064 | AL7: =I7/H7 -> 0.27073786
A8: =Analysis_Base!A8 -> INDF | B8: =Analysis_Base!B8 -> 2022 | C8: =VALUE(Analysis_Base!C8) -> 110830272000000 | D8: =VALUE(Analysis_Base!E8) -> 16350531000000 | E8: =VALUE(Analysis_Base!F8) -> 15524858000000 | F8: =VALUE(Analysis_Base!G8) -> 18792599000000 | G8: =VALUE(Analysis_Base!H8) -> 6359094000000 | H8: =VALUE(Analysis_Base!I8) -> 180433300000000 | I8: =VALUE(Analysis_Base!J8) -> 53843836000000 | J8: =VALUE(Analysis_Base!M8) -> 66249057000000 | K8: =VALUE(Analysis_Base!D8) -> 33971679000000 | L8: =VALUE(Analysis_Base!K8) -> 54876668000000 | M8: =VALUE(Analysis_Base!L8) -> 30725942000000 | N8: =IF(A8=A7,C8/C7-1,"") -> 0.11560303 | O8: =IF(A8=A7,D8/D7-1,"") -> -0.098212898 | P8: =IF(A8=A7,G8/G7-1,"") -> -0.17007528 | Q8: =IF(A8=A7,AG8/AG7-1,"") -> -0.072719806 | R8: =IF(A8=A7,AH8/AH7-1,"") -> -0.026523185 | S8: =K8/C8 -> 0.30651986 | T8: =D8/C8 -> 0.14752766 | U8: =E8/C8 -> 0.14007778 | V8: =F8/C8 -> 0.16956197 | W8: =G8/C8 -> 0.057376869 | X8: =G8/I8 -> 0.11810254 | Y8: =G8/H8 -> 0.035243461 | Z8: =L8/M8 -> 1.7860044 | AA8: =J8/I8 -> 1.2303926 | AB8: =J8/H8 -> 0.36716647 | AC8: =I8/H8 -> 0.29841407 | AD8: =VALUE(Analysis_Base!O8) -> -3899503000000 | AE8: =VALUE(Analysis_Base!P8) -> -14329188000000 | AF8: =VALUE(Analysis_Base!R8) -> -3979013000000 | AG8: =VALUE(Analysis_Base!N8) -> 13624195000000 | AH8: =VALUE(Analysis_Base!Q8) -> 9645182000000 | AI8: =AG8/C8 -> 0.12292846 | AJ8: =AH8/C8 -> 0.087026602 | AK8: =ABS(AF8)/AG8 -> 0.29205491 | AL8: =I8/H8 -> 0.29841407
A9: =Analysis_Base!A9 -> INDF | B9: =Analysis_Base!B9 -> 2023 | C9: =VALUE(Analysis_Base!C9) -> 111703611000000 | D9: =VALUE(Analysis_Base!E9) -> 19861872000000 | E9: =VALUE(Analysis_Base!F9) -> 19140009000000 | F9: =VALUE(Analysis_Base!G9) -> 20144409000000 | G9: =VALUE(Analysis_Base!H9) -> 8147019000000 | H9: =VALUE(Analysis_Base!I9) -> 186587957000000 | I9: =VALUE(Analysis_Base!J9) -> 59193013000000 | J9: =VALUE(Analysis_Base!M9) -> 64692665000000 | K9: =VALUE(Analysis_Base!D9) -> 36050469000000 | L9: =VALUE(Analysis_Base!K9) -> 63101797000000 | M9: =VALUE(Analysis_Base!L9) -> 32914504000000 | N9: =IF(A9=A8,C9/C8-1,"") -> 0.007879968 | O9: =IF(A9=A8,D9/D8-1,"") -> 0.21475394 | P9: =IF(A9=A8,G9/G8-1,"") -> 0.28116034 | Q9: =IF(A9=A8,AG9/AG8-1,"") -> 0.35498824 | R9: =IF(A9=A8,AH9/AH8-1,"") -> 0.50259062 | S9: =K9/C9 -> 0.32273325 | T9: =D9/C9 -> 0.17780868 | U9: =E9/C9 -> 0.17134638 | V9: =F9/C9 -> 0.18033803 | W9: =G9/C9 -> 0.072934249 | X9: =G9/I9 -> 0.13763481 | Y9: =G9/H9 -> 0.043663156 | Z9: =L9/M9 -> 1.9171426 | AA9: =J9/I9 -> 1.0929105 | AB9: =J9/H9 -> 0.34671404 | AC9: =I9/H9 -> 0.31723919 | AD9: =VALUE(Analysis_Base!O9) -> -10775851000000 | AE9: =VALUE(Analysis_Base!P9) -> -4889846000000 | AF9: =VALUE(Analysis_Base!R9) -> -3967864000000 | AG9: =VALUE(Analysis_Base!N9) -> 18460624000000 | AH9: =VALUE(Analysis_Base!Q9) -> 14492760000000 | AI9: =AG9/C9 -> 0.16526434 | AJ9: =AH9/C9 -> 0.12974299 | AK9: =ABS(AF9)/AG9 -> 0.21493661 | AL9: =I9/H9 -> 0.31723919
A10: =Analysis_Base!A10 -> MYOR | B10: =Analysis_Base!B10 -> 2020 | C10: =VALUE(Analysis_Base!C10) -> 24476953742651 | D10: =VALUE(Analysis_Base!E10) -> 3165621987673 | E10: =VALUE(Analysis_Base!F10) -> 3037712615943 | F10: =VALUE(Analysis_Base!G10) -> 2857436314408 | G10: =VALUE(Analysis_Base!H10) -> 2060631850945 | H10: =VALUE(Analysis_Base!I10) -> 19777500514550 | I10: =VALUE(Analysis_Base!J10) -> 11011069905567 | J10: =VALUE(Analysis_Base!M10) -> 4860827484888 | K10: =VALUE(Analysis_Base!D10) -> 7299122959685 | L10: =VALUE(Analysis_Base!K10) -> 12838729162094 | M10: =VALUE(Analysis_Base!L10) -> 3559336027729 | N10: =IF(A10=A9,C10/C9-1,"") | O10: =IF(A10=A9,D10/D9-1,"") | P10: =IF(A10=A9,G10/G9-1,"") | Q10: =IF(A10=A9,AG10/AG9-1,"") | R10: =IF(A10=A9,AH10/AH9-1,"") | S10: =K10/C10 -> 0.2982039 | T10: =D10/C10 -> 0.12933072 | U10: =E10/C10 -> 0.12410501 | V10: =F10/C10 -> 0.11673987 | W10: =G10/C10 -> 0.084186614 | X10: =G10/I10 -> 0.18714184 | Y10: =G10/H10 -> 0.10419071 | Z10: =L10/M10 -> 3.6070573 | AA10: =J10/I10 -> 0.44144915 | AB10: =J10/H10 -> 0.24577562 | AC10: =I10/H10 -> 0.55674729 | AD10: =VALUE(Analysis_Base!O10) -> -1111015237138 | AE10: =VALUE(Analysis_Base!P10) -> -1865848198703 | AF10: =VALUE(Analysis_Base!R10) -> -1155602411570 | AG10: =VALUE(Analysis_Base!N10) -> 3715832449186 | AH10: =VALUE(Analysis_Base!Q10) -> 2560230037616 | AI10: =AG10/C10 -> 0.15180943 | AJ10: =AH10/C10 -> 0.10459758 | AK10: =ABS(AF10)/AG10 -> 0.31099422 | AL10: =I10/H10 -> 0.55674729
A11: =Analysis_Base!A11 -> MYOR | B11: =Analysis_Base!B11 -> 2021 | C11: =VALUE(Analysis_Base!C11) -> 27904558322183 | D11: =VALUE(Analysis_Base!E11) -> 2001485741380 | E11: =VALUE(Analysis_Base!F11) -> 1870183771326 | F11: =VALUE(Analysis_Base!G11) -> 1804861101096 | G11: =VALUE(Analysis_Base!H11) -> 1186598590767 | H11: =VALUE(Analysis_Base!I11) -> 19917653265528 | I11: =VALUE(Analysis_Base!J11) -> 11118707150388 | J11: =VALUE(Analysis_Base!M11) -> 5133934187496 | K11: =VALUE(Analysis_Base!D11) -> 6922983508403 | L11: =VALUE(Analysis_Base!K11) -> 12969783874643 | M11: =VALUE(Analysis_Base!L11) -> 5570773468770 | N11: =IF(A11=A10,C11/C10-1,"") -> 0.14003395 | O11: =IF(A11=A10,D11/D10-1,"") -> -0.36774329 | P11: =IF(A11=A10,G11/G10-1,"") -> -0.42415789 | Q11: =IF(A11=A10,AG11/AG10-1,"") -> -0.71959042 | R11: =IF(A11=A10,AH11/AH10-1,"") -> -0.97479952 | S11: =K11/C11 -> 0.24809508 | T11: =D11/C11 -> 0.071726122 | U11: =E11/C11 -> 0.067020726 | V11: =F11/C11 -> 0.064679795 | W11: =G11/C11 -> 0.042523468 | X11: =G11/I11 -> 0.10672091 | Y11: =G11/H11 -> 0.059575221 | Z11: =L11/M11 -> 2.3281837 | AA11: =J11/I11 -> 0.46173841 | AB11: =J11/H11 -> 0.25775799 | AC11: =I11/H11 -> 0.55823379 | AD11: =VALUE(Analysis_Base!O11) -> -947614701926 | AE11: =VALUE(Analysis_Base!P11) -> -870693620125 | AF11: =VALUE(Analysis_Base!R11) -> -977435990290 | AG11: =VALUE(Analysis_Base!N11) -> 1041955003348 | AH11: =VALUE(Analysis_Base!Q11) -> 64519013058 | AI11: =AG11/C11 -> 0.037339957 | AJ11: =AH11/C11 -> 0.0023121317 | AK11: =ABS(AF11)/AG11 -> 0.93807889 | AL11: =I11/H11 -> 0.55823379
A12: =Analysis_Base!A12 -> MYOR | B12: =Analysis_Base!B12 -> 2022 | C12: =VALUE(Analysis_Base!C12) -> 30669405967404 | D12: =VALUE(Analysis_Base!E12) -> 3019424332266 | E12: =VALUE(Analysis_Base!F12) -> 2895240195831 | F12: =VALUE(Analysis_Base!G12) -> 2466196699030 | G12: =VALUE(Analysis_Base!H12) -> 1942229752036 | H12: =VALUE(Analysis_Base!I12) -> 22276160695411 | I12: =VALUE(Analysis_Base!J12) -> 12628400600637 | J12: =VALUE(Analysis_Base!M12) -> 5529177853189 | K12: =VALUE(Analysis_Base!D12) -> 6839423338924 | L12: =VALUE(Analysis_Base!K12) -> 14772623976128 | M12: =VALUE(Analysis_Base!L12) -> 5636627301308 | N12: =IF(A12=A11,C12/C11-1,"") -> 0.099082294 | O12: =IF(A12=A11,D12/D11-1,"") -> 0.50859148 | P12: =IF(A12=A11,G12/G11-1,"") -> 0.63680436 | Q12: =IF(A12=A11,AG12/AG11-1,"") -> 0.55435756 | R12: =IF(A12=A11,AH12/AH11-1,"") -> 0.71043937 | S12: =K12/C12 -> 0.22300475 | T12: =D12/C12 -> 0.098450695 | U12: =E12/C12 -> 0.094401574 | V12: =F12/C12 -> 0.080412275 | W12: =G12/C12 -> 0.063327922 | X12: =G12/I12 -> 0.15379855 | Y12: =G12/H12 -> 0.087188712 | Z12: =L12/M12 -> 2.6208268 | AA12: =J12/I12 -> 0.43783675 | AB12: =J12/H12 -> 0.24821054 | AC12: =I12/H12 -> 0.56690202 | AD12: =VALUE(Analysis_Base!O12) -> -1546563424787 | AE12: =VALUE(Analysis_Base!P12) -> -49224058856 | AF12: =VALUE(Analysis_Base!R12) -> -1509214777944 | AG12: =VALUE(Analysis_Base!N12) -> 1619570638186 | AH12: =VALUE(Analysis_Base!Q12) -> 110355860242 | AI12: =AG12/C12 -> 0.052807369 | AJ12: =AH12/C12 -> 0.0035982392 | AK12: =ABS(AF12)/AG12 -> 0.93186104 | AL12: =I12/H12 -> 0.56690202
A13: =Analysis_Base!A13 -> MYOR | B13: =Analysis_Base!B13 -> 2023 | C13: =VALUE(Analysis_Base!C13) -> 31485008185525 | D13: =VALUE(Analysis_Base!E13) -> 4517736259342 | E13: =VALUE(Analysis_Base!F13) -> 4396292972270 | F13: =VALUE(Analysis_Base!G13) -> 4335787550846 | G13: =VALUE(Analysis_Base!H13) -> 3193816276615 | H13: =VALUE(Analysis_Base!I13) -> 23870404962472 | I13: =VALUE(Analysis_Base!J13) -> 15039487611663 | J13: =VALUE(Analysis_Base!M13) -> 4267410076475 | K13: =VALUE(Analysis_Base!D13) -> 8407777758683 | L13: =VALUE(Analysis_Base!K13) -> 14738922387529 | M13: =VALUE(Analysis_Base!L13) -> 4013200501414 | N13: =IF(A13=A12,C13/C12-1,"") -> 0.026593349 | O13: =IF(A13=A12,D13/D12-1,"") -> 0.49622437 | P13: =IF(A13=A12,G13/G12-1,"") -> 0.64440704 | Q13: =IF(A13=A12,AG13/AG12-1,"") -> 2.2472693 | R13: =IF(A13=A12,AH13/AH12-1,"") -> 23.76944 | S13: =K13/C13 -> 0.26704067 | T13: =D13/C13 -> 0.14348849 | U13: =E13/C13 -> 0.13963131 | V13: =F13/C13 -> 0.13770959 | W13: =G13/C13 -> 0.10143927 | X13: =G13/I13 -> 0.21236204 | Y13: =G13/H13 -> 0.13379816 | Z13: =L13/M13 -> 3.6726105 | AA13: =J13/I13 -> 0.28374704 | AB13: =J13/H13 -> 0.1787741 | AC13: =I13/H13 -> 0.63004744 | AD13: =VALUE(Analysis_Base!O13) -> -2359457241900 | AE13: =VALUE(Analysis_Base!P13) -> -1975978291736 | AF13: =VALUE(Analysis_Base!R13) -> -2525729079182 | AG13: =VALUE(Analysis_Base!N13) -> 5259181989696 | AH13: =VALUE(Analysis_Base!Q13) -> 2733452910514 | AI13: =AG13/C13 -> 0.16703766 | AJ13: =AH13/C13 -> 0.086817602 | AK13: =ABS(AF13)/AG13 -> 0.48025132 | AL13: =I13/H13 -> 0.63004744
... A17: =Analysis_Base!A17 -> UNVR | B17: =Analysis_Base!B17 -> 2023 | C17: =VALUE(Analysis_Base!C17) -> 38611401000000 | D17: =VALUE(Analysis_Base!E17) -> 6690717000000 | E17: =VALUE(Analysis_Base!F17) -> 6307846000000 | F17: =VALUE(Analysis_Base!G17) -> 6279283000000 | G17: =VALUE(Analysis_Base!H17) -> 4800940000000 | H17: =VALUE(Analysis_Base!I17) -> 16664086000000 | I17: =VALUE(Analysis_Base!J17) -> 3381238000000 | J17: =VALUE(Analysis_Base!M17) -> 750783000000 | K17: =VALUE(Analysis_Base!D17) -> 19194514000000 | L17: =VALUE(Analysis_Base!K17) -> 6191839000000 | M17: =VALUE(Analysis_Base!L17) -> 11223968000000 | N17: =IF(A17=A16,C17/C16-1,"") -> -0.063259359 | O17: =IF(A17=A16,D17/D16-1,"") -> -0.10844694 | P17: =IF(A17=A16,G17/G16-1,"") -> -0.10509713 | Q17: =IF(A17=A16,AG17/AG16-1,"") -> -0.11700648 | R17: =IF(A17=A16,AH17/AH16-1,"") -> -0.15356305 | S17: =K17/C17 -> 0.49712037 | T17: =D17/C17 -> 0.17328346 | U17: =E17/C17 -> 0.16336745 | V17: =F17/C17 -> 0.16262769 | W17: =G17/C17 -> 0.12433996 | X17: =G17/I17 -> 1.4198764 | Y17: =G17/H17 -> 0.28810101 | Z17: =L17/M17 -> 0.55166221 | AA17: =J17/I17 -> 0.22204382 | AB17: =J17/H17 -> 0.045053956 | AC17: =I17/H17 -> 0.2029057 | AD17: =VALUE(Analysis_Base!O17) -> -829323000000 | AE17: =VALUE(Analysis_Base!P17) -> -5771276000000 | AF17: =VALUE(Analysis_Base!R17) -> -835028000000 | AG17: =VALUE(Analysis_Base!N17) -> 7118088000000 | AH17: =VALUE(Analysis_Base!Q17) -> 6283060000000 | AI17: =AG17/C17 -> 0.18435197 | AJ17: =AH17/C17 -> 0.16272551 | AK17: =ABS(AF17)/AG17 -> 0.11731072 | AL17: =I17/H17 -> 0.2029057
